django_glitter_news-0.3.3.dist-info/METADATA
django_glitter_news-0.3.3.dist-info/RECORD
django_glitter_news-0.3.3.dist-info/WHEEL
django_glitter_news-0.3.3.dist-info/top_level.txt
glitter_news/__init__.py
glitter_news/admin.py
glitter_news/apps.py
glitter_news/feeds.py
glitter_news/glitter_apps.py
glitter_news/managers.py
glitter_news/models.py
glitter_news/search_indexes.py
glitter_news/urls.py
glitter_news/views.py
glitter_news/migrations/0001_initial.py
glitter_news/migrations/0002_post_author.py
glitter_news/migrations/0003_post_tags.py
glitter_news/migrations/0004_remove_post_date_url.py
glitter_news/migrations/0005_add_sortable.py
glitter_news/migrations/0006_populate_category_order.py
glitter_news/migrations/0007_latestnewsblock_tags.py
glitter_news/migrations/0008_post_is_sticky.py
glitter_news/migrations/0009_sitcky_ordering.py
glitter_news/migrations/__init__.py
glitter_news/templates/search/indexes/glitter_news/post_text.txt
glitter_news/templatetags/__init__.py
glitter_news/templatetags/news_tags.py
