Metadata-Version: 2.1
Name: django-glitter-news
Version: 0.3.3
Summary: Django Glitter News for Django
Home-page: https://github.com/blancltd/django-glitter-news
Maintainer: Blanc Ltd
Maintainer-email: studio@blanc.ltd.uk
License: BSD
Platform: any
Classifier: Environment :: Web Environment
Classifier: Framework :: Django
Classifier: License :: OSI Approved :: BSD License
Classifier: Operating System :: OS Independent
Classifier: Programming Language :: Python
Classifier: Programming Language :: Python :: 2
Classifier: Programming Language :: Python :: 2.7
Classifier: Programming Language :: Python :: 3
Classifier: Programming Language :: Python :: 3.3
Classifier: Programming Language :: Python :: 3.4
Classifier: Programming Language :: Python :: 3.5
Requires-Dist: django-glitter
Requires-Dist: django-taggit (>=0.21.3)
Requires-Dist: django-admin-sortable (>=2.0.0)
